Metadata-Version: 2.1
Name: array_api_compat
Version: 1.9.1
Summary: A wrapper around NumPy and other array libraries to make them compatible with the Array API standard
Home-page: https://data-apis.org/array-api-compat/
Author: Consortium for Python Data API Standards
License: MIT
Classifier: Programming Language :: Python :: 3
Classifier: Programming Language :: Python :: 3.9
Classifier: Programming Language :: Python :: 3.10
Classifier: Programming Language :: Python :: 3.11
Classifier: Programming Language :: Python :: 3.12
Classifier: Programming Language :: Python :: 3.13
Classifier: License :: OSI Approved :: MIT License
Classifier: Operating System :: OS Independent
Requires-Python: >=3.9
License-File: LICENSE
Provides-Extra: numpy
Requires-Dist: numpy; extra == "numpy"
Provides-Extra: cupy
Requires-Dist: cupy; extra == "cupy"
Provides-Extra: jax
Requires-Dist: jax; extra == "jax"
Provides-Extra: pytorch
Requires-Dist: pytorch; extra == "pytorch"
Provides-Extra: dask
Requires-Dist: dask; extra == "dask"
Provides-Extra: sparse
Requires-Dist: sparse>=0.15.1; extra == "sparse"
